nicegui/.syncignore
nicegui/__init__.py
nicegui/air.py
nicegui/api_router.py
nicegui/app/__init__.py
nicegui/app/app.py
nicegui/app/app_config.py
nicegui/app/range_response.py
nicegui/awaitable_response.py
nicegui/background_tasks.py
nicegui/binding.py
nicegui/classes.py
nicegui/client.py
nicegui/context.py
nicegui/core.py
nicegui/dataclasses.py
nicegui/dependencies.py
nicegui/element.py
nicegui/element_filter.py
nicegui/elements/__init__.py
nicegui/elements/aggrid/__init__.py
nicegui/elements/aggrid/aggrid.js
nicegui/elements/aggrid/aggrid.py
nicegui/elements/aggrid/dist/index.js
nicegui/elements/aggrid/dist/index.js.map
nicegui/elements/aggrid/package-lock.json
nicegui/elements/aggrid/package.json
nicegui/elements/aggrid/rollup.config.mjs
nicegui/elements/aggrid/src/index.mjs
nicegui/elements/audio.js
nicegui/elements/audio.py
nicegui/elements/avatar.py
nicegui/elements/badge.py
nicegui/elements/button.py
nicegui/elements/button_dropdown.py
nicegui/elements/button_group.py
nicegui/elements/card.py
nicegui/elements/carousel.py
nicegui/elements/chat_message.py
nicegui/elements/checkbox.py
nicegui/elements/chip.py
nicegui/elements/choice_element.py
nicegui/elements/code.js
nicegui/elements/code.py
nicegui/elements/codemirror/__init__.py
nicegui/elements/codemirror/codemirror.js
nicegui/elements/codemirror/codemirror.py
nicegui/elements/codemirror/dist/apl-CXdQSnD-.js
nicegui/elements/codemirror/dist/apl-CXdQSnD-.js.map
nicegui/elements/codemirror/dist/asciiarmor-D5V0T9Cu.js
nicegui/elements/codemirror/dist/asciiarmor-D5V0T9Cu.js.map
nicegui/elements/codemirror/dist/asn1-DWPaVWf6.js
nicegui/elements/codemirror/dist/asn1-DWPaVWf6.js.map
nicegui/elements/codemirror/dist/asterisk-B46aRdXb.js
nicegui/elements/codemirror/dist/asterisk-B46aRdXb.js.map
nicegui/elements/codemirror/dist/brainfuck-CtZaYBKt.js
nicegui/elements/codemirror/dist/brainfuck-CtZaYBKt.js.map
nicegui/elements/codemirror/dist/clike-hUAFEsGo.js
nicegui/elements/codemirror/dist/clike-hUAFEsGo.js.map
nicegui_evnchn_pyodide-3.4.1.post14.dist-info/METADATA
nicegui_evnchn_pyodide-3.4.1.post14.dist-info/WHEEL
nicegui_evnchn_pyodide-3.4.1.post14.dist-info/entry_points.txt
nicegui_evnchn_pyodide-3.4.1.post14.dist-info/licenses/LICENSE
nicegui_evnchn_pyodide-3.4.1.post14.dist-info/RECORD
