Metadata-Version: 2.4
Name: nicegui-evnchn-pyodide
Version: 3.4.1.post14
Summary: Create web-based user interfaces with Python. The nice way. (Pyodide-compatible fork)
License-Expression: MIT
License-File: LICENSE
Keywords: gui,ui,web,interface,live
Author: Zauberzeug GmbH
Author-email: info@zauberzeug.com
Requires-Python: >=3.9,<4
Classifier: Programming Language :: Python :: 3
Classifier: Programming Language :: Python :: 3.9
Classifier: Programming Language :: Python :: 3.10
Classifier: Programming Language :: Python :: 3.11
Classifier: Programming Language :: Python :: 3.12
Classifier: Programming Language :: Python :: 3.13
Classifier: Programming Language :: Python :: 3.14
Provides-Extra: highcharts
Provides-Extra: matplotlib
Provides-Extra: native
Provides-Extra: plotly
Provides-Extra: redis
Provides-Extra: server
Requires-Dist: Pygments (>=2.15.1,<3.0.0)
Requires-Dist: aiohttp (>=3.10.2) ; extra == "server"
Requires-Dist: docutils (>=0.19.0)
Requires-Dist: jinja2 (>=3.1.6,<4)
Requires-Dist: markdown2 (>=2.4.7,!=2.4.11)
Requires-Dist: matplotlib (>=3.5.0,<4) ; extra == "matplotlib"
Requires-Dist: nicegui-highcharts (>=2.0.2,<3) ; extra == "highcharts"
Requires-Dist: orjson (>=3.9.15) ; (platform_machine != "i386" and platform_machine != "i686" and platform_python_implementation != "PyPy") and (extra == "server")
Requires-Dist: plotly (>=5.13,<7.0) ; extra == "plotly"
Requires-Dist: pywebview (>=5.0.1,<7) ; extra == "native"
Requires-Dist: redis (>=4.0.0) ; extra == "redis"
Requires-Dist: typing-extensions (>=4.0.0)
Requires-Dist: uvicorn[standard] (>=0.22.0) ; extra == "server"
Requires-Dist: watchfiles (>=0.18.1) ; extra == "server"
Project-URL: Repository, https://github.com/zauberzeug/nicegui
